odoo8_addon_l10n_ar_wsfe_perceptions-8.0.1.0.0-py2.7-nspkg.pth
odoo_addons/l10n_ar_wsfe_perceptions/.gitignore
odoo_addons/l10n_ar_wsfe_perceptions/__openerp__.py
odoo_addons/l10n_ar_wsfe_perceptions/__init__.py
odoo_addons/l10n_ar_wsfe_perceptions/invoice.py
odoo8_addon_l10n_ar_wsfe_perceptions-8.0.1.0.0.dist-info/top_level.txt
odoo8_addon_l10n_ar_wsfe_perceptions-8.0.1.0.0.dist-info/WHEEL
odoo8_addon_l10n_ar_wsfe_perceptions-8.0.1.0.0.dist-info/RECORD
odoo8_addon_l10n_ar_wsfe_perceptions-8.0.1.0.0.dist-info/metadata.json
odoo8_addon_l10n_ar_wsfe_perceptions-8.0.1.0.0.dist-info/DESCRIPTION.rst
odoo8_addon_l10n_ar_wsfe_perceptions-8.0.1.0.0.dist-info/METADATA
odoo8_addon_l10n_ar_wsfe_perceptions-8.0.1.0.0.dist-info/namespace_packages.txt
